[{"id":1,"first_name":"Alvie","last_name":"Musgrave","email":"amusgrave0@cocolog-nifty.com","date_of_birth":"12/20/1989","age":34,"country":"China","phone":"6885341952"},
{"id":2,"first_name":"Rebeka","last_name":"Huffy","email":"rhuffy1@wired.com","date_of_birth":"7/14/2006","age":51,"country":"China","phone":"3529974464"},
{"id":3,"first_name":"Zedekiah","last_name":"Wrigglesworth","email":"zwrigglesworth2@xing.com","date_of_birth":"9/10/1993","age":53,"country":"China","phone":"1952168711"},
{"id":4,"first_name":"Ronalda","last_name":"Vanshin","email":"rvanshin3@zdnet.com","date_of_birth":"11/3/2002","age":25,"country":"Portugal","phone":"9689888967"},
{"id":5,"first_name":"Bernita","last_name":"McGlashan","email":"bmcglashan4@about.me","date_of_birth":"3/16/2015","age":38,"country":"Sweden","phone":"4779040247"},
{"id":6,"first_name":"Gae","last_name":"Nixon","email":"gnixon5@virginia.edu","date_of_birth":"5/19/1989","age":26,"country":"China","phone":"3506993091"},
{"id":7,"first_name":"Drud","last_name":"Reece","email":"dreece6@ow.ly","date_of_birth":"5/23/1986","age":20,"country":"Indonesia","phone":"1438203183"},
{"id":8,"first_name":"Mallory","last_name":"Cundy","email":"mcundy7@techcrunch.com","date_of_birth":"10/7/2010","age":24,"country":"Palestinian Territory","phone":"9809771803"},
{"id":9,"first_name":"Claire","last_name":"Fedorchenko","email":"cfedorchenko8@canalblog.com","date_of_birth":"8/11/2013","age":29,"country":"Japan","phone":"8145312261"},
{"id":10,"first_name":"Merline","last_name":"Procter","email":"mprocter9@dyndns.org","date_of_birth":"5/24/1975","age":33,"country":"China","phone":"7606102007"},
{"id":11,"first_name":"Lynsey","last_name":"Partridge","email":"lpartridgea@sbwire.com","date_of_birth":"1/21/2005","age":50,"country":"Nigeria","phone":"5795307884"},
{"id":12,"first_name":"Gardie","last_name":"Pinkett","email":"gpinkettb@hao123.com","date_of_birth":"6/23/1996","age":34,"country":"China","phone":"5006859336"},
{"id":13,"first_name":"Elmira","last_name":"Maylard","email":"emaylardc@alexa.com","date_of_birth":"10/23/1976","age":52,"country":"Nigeria","phone":"6241986925"},
{"id":14,"first_name":"Berk","last_name":"Dowall","email":"bdowalld@unicef.org","date_of_birth":"4/8/1975","age":22,"country":"Poland","phone":"7465104471"},
{"id":15,"first_name":"Annadiane","last_name":"Seamons","email":"aseamonse@sohu.com","date_of_birth":"6/5/1971","age":27,"country":"Indonesia","phone":"1759006962"},
{"id":16,"first_name":"Willard","last_name":"Iggalden","email":"wiggaldenf@sogou.com","date_of_birth":"4/14/1981","age":30,"country":"China","phone":"4766146438"},
{"id":17,"first_name":"Thorvald","last_name":"Birckmann","email":"tbirckmanng@blinklist.com","date_of_birth":"12/29/2014","age":29,"country":"Indonesia","phone":"6342618446"},
{"id":18,"first_name":"Helen-elizabeth","last_name":"Bassford","email":"hbassfordh@topsy.com","date_of_birth":"11/18/1979","age":26,"country":"Russia","phone":"3926441642"},
{"id":19,"first_name":"Burty","last_name":"Ivanenko","email":"bivanenkoi@loc.gov","date_of_birth":"6/19/2004","age":19,"country":"Sierra Leone","phone":"7236637376"},
{"id":20,"first_name":"Fergus","last_name":"Yewdale","email":"fyewdalej@google.de","date_of_birth":"10/18/1973","age":27,"country":"Colombia","phone":"7378530052"},
{"id":21,"first_name":"Edee","last_name":"Tarply","email":"etarplyk@woothemes.com","date_of_birth":"7/30/2009","age":22,"country":"Thailand","phone":"5776106613"},
{"id":22,"first_name":"Bruno","last_name":"Dibson","email":"bdibsonl@freewebs.com","date_of_birth":"4/2/1982","age":58,"country":"Afghanistan","phone":"4094531135"},
{"id":23,"first_name":"Emily","last_name":"Leas","email":"eleasm@ucsd.edu","date_of_birth":"4/13/2015","age":38,"country":"France","phone":"2128275217"},
{"id":24,"first_name":"Jan","last_name":"Ormond","email":"jormondn@i2i.jp","date_of_birth":"12/19/1990","age":29,"country":"Argentina","phone":"2879008836"},
{"id":25,"first_name":"Gail","last_name":"Rosenbloom","email":"grosenbloomo@ucoz.com","date_of_birth":"9/27/2020","age":20,"country":"Russia","phone":"1936692731"},
{"id":26,"first_name":"Kalila","last_name":"O' Dornan","email":"kodornanp@buzzfeed.com","date_of_birth":"3/16/2014","age":46,"country":"Ethiopia","phone":"9989817676"},
{"id":27,"first_name":"Ripley","last_name":"Ailward","email":"railwardq@forbes.com","date_of_birth":"6/21/2006","age":42,"country":"France","phone":"2366332327"},
{"id":28,"first_name":"Alvina","last_name":"Widocks","email":"awidocksr@ed.gov","date_of_birth":"8/9/1997","age":55,"country":"Mexico","phone":"3585467953"},
{"id":29,"first_name":"Fred","last_name":"Killock","email":"fkillocks@europa.eu","date_of_birth":"2/27/1993","age":38,"country":"China","phone":"4478604930"},
{"id":30,"first_name":"Sydney","last_name":"Levecque","email":"slevecquet@xing.com","date_of_birth":"5/1/1994","age":56,"country":"Indonesia","phone":"5427215275"},
{"id":31,"first_name":"Manny","last_name":"Bradley","email":"mbradleyu@miibeian.gov.cn","date_of_birth":"2/12/1987","age":26,"country":"Germany","phone":"5071631409"},
{"id":32,"first_name":"Darcie","last_name":"Buddle","email":"dbuddlev@desdev.cn","date_of_birth":"5/25/2015","age":38,"country":"Indonesia","phone":"6418928981"},
{"id":33,"first_name":"Lissa","last_name":"Peacher","email":"lpeacherw@businessweek.com","date_of_birth":"4/19/1972","age":48,"country":"China","phone":"4492097712"},
{"id":34,"first_name":"Ogdan","last_name":"Chastang","email":"ochastangx@alexa.com","date_of_birth":"8/16/2016","age":54,"country":"China","phone":"2778303191"},
{"id":35,"first_name":"Catina","last_name":"Dericut","email":"cdericuty@lycos.com","date_of_birth":"2/14/1987","age":29,"country":"Portugal","phone":"6642124758"},
{"id":36,"first_name":"Tully","last_name":"Jerosch","email":"tjeroschz@theguardian.com","date_of_birth":"2/20/2019","age":43,"country":"Serbia","phone":"4846693972"},
{"id":37,"first_name":"Reider","last_name":"Stonhewer","email":"rstonhewer10@dot.gov","date_of_birth":"1/14/2013","age":55,"country":"Japan","phone":"4935666199"},
{"id":38,"first_name":"Yettie","last_name":"Wint","email":"ywint11@netvibes.com","date_of_birth":"4/13/2004","age":45,"country":"Philippines","phone":"2036095004"},
{"id":39,"first_name":"Iggie","last_name":"Gilburt","email":"igilburt12@themeforest.net","date_of_birth":"6/21/2019","age":22,"country":"China","phone":"5653098072"},
{"id":40,"first_name":"Bernice","last_name":"Cogzell","email":"bcogzell13@wsj.com","date_of_birth":"8/8/1991","age":41,"country":"Sweden","phone":"1499679656"},
{"id":41,"first_name":"Spense","last_name":"Sjostrom","email":"ssjostrom14@shop-pro.jp","date_of_birth":"8/8/1971","age":21,"country":"Democratic Republic of the Congo","phone":"6021273952"},
{"id":42,"first_name":"Purcell","last_name":"Ayce","email":"payce15@tiny.cc","date_of_birth":"9/2/2007","age":35,"country":"Philippines","phone":"1401338408"},
{"id":43,"first_name":"Urban","last_name":"Safell","email":"usafell16@whitehouse.gov","date_of_birth":"10/23/2008","age":55,"country":"China","phone":"9108015232"},
{"id":44,"first_name":"Fiona","last_name":"Cowing","email":"fcowing17@theglobeandmail.com","date_of_birth":"11/10/1993","age":29,"country":"Peru","phone":"6645861682"},
{"id":45,"first_name":"Netta","last_name":"Casolla","email":"ncasolla18@gravatar.com","date_of_birth":"5/27/2020","age":22,"country":"Russia","phone":"8106125353"},
{"id":46,"first_name":"Reynold","last_name":"Alleyn","email":"ralleyn19@nih.gov","date_of_birth":"5/14/2000","age":47,"country":"Brazil","phone":"8941289691"},
{"id":47,"first_name":"Deana","last_name":"Orriss","email":"dorriss1a@nymag.com","date_of_birth":"1/14/2001","age":26,"country":"China","phone":"4518973369"},
{"id":48,"first_name":"Templeton","last_name":"Mulchrone","email":"tmulchrone1b@bluehost.com","date_of_birth":"11/11/2009","age":47,"country":"Russia","phone":"8445848714"},
{"id":49,"first_name":"Vladimir","last_name":"Legate","email":"vlegate1c@technorati.com","date_of_birth":"3/22/2007","age":47,"country":"Portugal","phone":"5598921253"},
{"id":50,"first_name":"Twila","last_name":"Manueli","email":"tmanueli1d@ucoz.com","date_of_birth":"2/17/1973","age":56,"country":"El Salvador","phone":"4206445811"},
{"id":51,"first_name":"Lila","last_name":"Turfs","email":"lturfs1e@smugmug.com","date_of_birth":"11/26/1979","age":27,"country":"Philippines","phone":"9337280180"},
{"id":52,"first_name":"Skippie","last_name":"Axtell","email":"saxtell1f@nifty.com","date_of_birth":"12/1/2017","age":42,"country":"China","phone":"3364389461"},
{"id":53,"first_name":"Tina","last_name":"Hendron","email":"thendron1g@irs.gov","date_of_birth":"3/12/1973","age":32,"country":"Germany","phone":"6458119601"},
{"id":54,"first_name":"Marmaduke","last_name":"Sanderson","email":"msanderson1h@dropbox.com","date_of_birth":"3/24/1974","age":54,"country":"Indonesia","phone":"1254820998"},
{"id":55,"first_name":"Mata","last_name":"Delea","email":"mdelea1i@spotify.com","date_of_birth":"6/2/1978","age":32,"country":"Canada","phone":"6421951409"},
{"id":56,"first_name":"Charmane","last_name":"Blazevic","email":"cblazevic1j@angelfire.com","date_of_birth":"3/31/2016","age":41,"country":"Russia","phone":"1039805970"},
{"id":57,"first_name":"April","last_name":"Latchford","email":"alatchford1k@geocities.jp","date_of_birth":"1/24/1975","age":18,"country":"Macedonia","phone":"4393046789"},
{"id":58,"first_name":"Lenci","last_name":"Smowton","email":"lsmowton1l@hhs.gov","date_of_birth":"5/31/2004","age":24,"country":"Belarus","phone":"6755118331"},
{"id":59,"first_name":"Aveline","last_name":"Boswell","email":"aboswell1m@fda.gov","date_of_birth":"3/2/1988","age":24,"country":"Brazil","phone":"2806437279"},
{"id":60,"first_name":"Bebe","last_name":"Swinden","email":"bswinden1n@prnewswire.com","date_of_birth":"5/6/2011","age":49,"country":"Brazil","phone":"7427993927"},
{"id":61,"first_name":"Carolynn","last_name":"Langworthy","email":"clangworthy1o@hhs.gov","date_of_birth":"10/5/1974","age":42,"country":"China","phone":"6989253106"},
{"id":62,"first_name":"Gerry","last_name":"Girault","email":"ggirault1p@senate.gov","date_of_birth":"2/4/1980","age":36,"country":"Mexico","phone":"6677867118"},
{"id":63,"first_name":"Solly","last_name":"Fitchell","email":"sfitchell1q@a8.net","date_of_birth":"1/16/2008","age":40,"country":"Poland","phone":"1037064906"},
{"id":64,"first_name":"Brier","last_name":"Shout","email":"bshout1r@yahoo.com","date_of_birth":"3/26/1975","age":57,"country":"Russia","phone":"1834450969"},
{"id":65,"first_name":"Garwood","last_name":"Balderstone","email":"gbalderstone1s@tripod.com","date_of_birth":"8/21/1996","age":35,"country":"Peru","phone":"6932654795"},
{"id":66,"first_name":"Paddie","last_name":"Cogswell","email":"pcogswell1t@storify.com","date_of_birth":"9/28/2012","age":57,"country":"China","phone":"9665598992"},
{"id":67,"first_name":"Zita","last_name":"Worvill","email":"zworvill1u@bing.com","date_of_birth":"8/11/1992","age":51,"country":"Indonesia","phone":"8967265117"},
{"id":68,"first_name":"Paloma","last_name":"Edwick","email":"pedwick1v@hhs.gov","date_of_birth":"5/8/1992","age":57,"country":"Russia","phone":"6522519999"},
{"id":69,"first_name":"Leodora","last_name":"Anthonies","email":"lanthonies1w@sbwire.com","date_of_birth":"2/19/2016","age":56,"country":"China","phone":"5589970865"},
{"id":70,"first_name":"Danielle","last_name":"Scare","email":"dscare1x@engadget.com","date_of_birth":"10/4/2008","age":41,"country":"China","phone":"5233334872"},
{"id":71,"first_name":"Leigh","last_name":"Ecclesall","email":"lecclesall1y@thetimes.co.uk","date_of_birth":"3/1/1975","age":46,"country":"China","phone":"9743681039"},
{"id":72,"first_name":"Leonerd","last_name":"McIlveen","email":"lmcilveen1z@elpais.com","date_of_birth":"8/5/2007","age":24,"country":"Croatia","phone":"7104771832"},
{"id":73,"first_name":"Tisha","last_name":"Reckless","email":"treckless20@economist.com","date_of_birth":"4/9/2020","age":41,"country":"Afghanistan","phone":"6766823240"},
{"id":74,"first_name":"Brenna","last_name":"Mathan","email":"bmathan21@sun.com","date_of_birth":"3/18/2006","age":35,"country":"Spain","phone":"4182209551"},
{"id":75,"first_name":"Taite","last_name":"Boyton","email":"tboyton22@imageshack.us","date_of_birth":"10/4/2000","age":33,"country":"Kuwait","phone":"3728364723"},
{"id":76,"first_name":"Ariel","last_name":"Whitters","email":"awhitters23@virginia.edu","date_of_birth":"11/28/1994","age":50,"country":"Russia","phone":"2568176779"},
{"id":77,"first_name":"Bryant","last_name":"Mayling","email":"bmayling24@netscape.com","date_of_birth":"9/14/2012","age":30,"country":"China","phone":"4772277612"},
{"id":78,"first_name":"Selie","last_name":"Middle","email":"smiddle25@dion.ne.jp","date_of_birth":"4/6/2000","age":33,"country":"Brazil","phone":"5591017457"},
{"id":79,"first_name":"Shellie","last_name":"Hollindale","email":"shollindale26@state.tx.us","date_of_birth":"11/30/2003","age":44,"country":"China","phone":"2693706351"},
{"id":80,"first_name":"Idaline","last_name":"Watson","email":"iwatson27@csmonitor.com","date_of_birth":"2/21/1981","age":33,"country":"Finland","phone":"6124278535"},
{"id":81,"first_name":"Rochella","last_name":"Le Provest","email":"rleprovest28@xing.com","date_of_birth":"5/19/1997","age":18,"country":"Peru","phone":"7979178144"},
{"id":82,"first_name":"Sid","last_name":"Blincko","email":"sblincko29@china.com.cn","date_of_birth":"8/16/1987","age":39,"country":"Peru","phone":"1606207786"},
{"id":83,"first_name":"Janis","last_name":"McVeighty","email":"jmcveighty2a@techcrunch.com","date_of_birth":"9/5/1988","age":57,"country":"China","phone":"3491283838"},
{"id":84,"first_name":"Russell","last_name":"Hulles","email":"rhulles2b@illinois.edu","date_of_birth":"1/18/1998","age":34,"country":"Japan","phone":"8564775847"},
{"id":85,"first_name":"Nowell","last_name":"Katt","email":"nkatt2c@vk.com","date_of_birth":"1/9/2006","age":41,"country":"Greece","phone":"4458536798"},
{"id":86,"first_name":"Gillan","last_name":"Da Costa","email":"gdacosta2d@go.com","date_of_birth":"5/20/2020","age":45,"country":"Kazakhstan","phone":"2292337497"},
{"id":87,"first_name":"Lynette","last_name":"Lince","email":"llince2e@altervista.org","date_of_birth":"7/11/2005","age":39,"country":"Russia","phone":"9254962071"},
{"id":88,"first_name":"Kristen","last_name":"Rossborough","email":"krossborough2f@foxnews.com","date_of_birth":"6/15/1996","age":28,"country":"El Salvador","phone":"1578969341"},
{"id":89,"first_name":"Brant","last_name":"Steinson","email":"bsteinson2g@usa.gov","date_of_birth":"10/25/1976","age":51,"country":"Philippines","phone":"3066803244"},
{"id":90,"first_name":"Carol-jean","last_name":"Tudball","email":"ctudball2h@macromedia.com","date_of_birth":"10/9/1986","age":56,"country":"Indonesia","phone":"4313656312"},
{"id":91,"first_name":"Engelbert","last_name":"Newlin","email":"enewlin2i@tinyurl.com","date_of_birth":"6/30/1989","age":48,"country":"Czech Republic","phone":"2386116966"},
{"id":92,"first_name":"Dennis","last_name":"Dungate","email":"ddungate2j@biglobe.ne.jp","date_of_birth":"11/29/1980","age":50,"country":"United States","phone":"2024319490"},
{"id":93,"first_name":"Camila","last_name":"Geffen","email":"cgeffen2k@indiegogo.com","date_of_birth":"8/31/2006","age":50,"country":"France","phone":"7524678252"},
{"id":94,"first_name":"Neil","last_name":"Cozins","email":"ncozins2l@redcross.org","date_of_birth":"12/21/1970","age":48,"country":"Panama","phone":"8608302661"},
{"id":95,"first_name":"Birk","last_name":"Sawart","email":"bsawart2m@constantcontact.com","date_of_birth":"1/22/1977","age":44,"country":"Zimbabwe","phone":"7175642234"},
{"id":96,"first_name":"Jeanne","last_name":"Davie","email":"jdavie2n@berkeley.edu","date_of_birth":"5/30/2002","age":31,"country":"Ukraine","phone":"4716998429"},
{"id":97,"first_name":"Tove","last_name":"Puckrin","email":"tpuckrin2o@alexa.com","date_of_birth":"10/8/2005","age":39,"country":"Philippines","phone":"9172950875"},
{"id":98,"first_name":"Margo","last_name":"Arnison","email":"marnison2p@hc360.com","date_of_birth":"12/10/1990","age":48,"country":"Sweden","phone":"9281191520"},
{"id":99,"first_name":"Trudy","last_name":"Kolakovic","email":"tkolakovic2q@nba.com","date_of_birth":"1/7/1975","age":37,"country":"Portugal","phone":"2505608691"},
{"id":100,"first_name":"Alan","last_name":"MacRedmond","email":"amacredmond2r@wikia.com","date_of_birth":"6/5/2001","age":50,"country":"Cameroon","phone":"7597703528"},
{"id":101,"first_name":"Rochella","last_name":"Charge","email":"rcharge2s@addthis.com","date_of_birth":"10/17/1980","age":20,"country":"Philippines","phone":"9069538456"},
{"id":102,"first_name":"Richmound","last_name":"Turrell","email":"rturrell2t@latimes.com","date_of_birth":"2/27/2001","age":30,"country":"Philippines","phone":"6246522146"},
{"id":103,"first_name":"Brandie","last_name":"Petracci","email":"bpetracci2u@blogspot.com","date_of_birth":"4/21/1979","age":31,"country":"Indonesia","phone":"9098911532"},
{"id":104,"first_name":"Arlyn","last_name":"Stirland","email":"astirland2v@army.mil","date_of_birth":"6/23/1989","age":58,"country":"United Arab Emirates","phone":"9007345169"},
{"id":105,"first_name":"Rodrigo","last_name":"Pinckard","email":"rpinckard2w@economist.com","date_of_birth":"2/5/1980","age":32,"country":"Philippines","phone":"2533738094"},
{"id":106,"first_name":"Fowler","last_name":"Stapylton","email":"fstapylton2x@opera.com","date_of_birth":"6/23/1999","age":24,"country":"Indonesia","phone":"1512714087"},
{"id":107,"first_name":"Lin","last_name":"Pothbury","email":"lpothbury2y@nsw.gov.au","date_of_birth":"4/16/2012","age":58,"country":"Sri Lanka","phone":"4787566538"},
{"id":108,"first_name":"Evelin","last_name":"Kenderdine","email":"ekenderdine2z@ebay.co.uk","date_of_birth":"8/29/1997","age":26,"country":"Philippines","phone":"9743761354"},
{"id":109,"first_name":"Ware","last_name":"Sherbrooke","email":"wsherbrooke30@bbc.co.uk","date_of_birth":"3/31/2011","age":28,"country":"Brazil","phone":"4522350292"},
{"id":110,"first_name":"Tommie","last_name":"Mapledoore","email":"tmapledoore31@yandex.ru","date_of_birth":"1/31/2009","age":40,"country":"Ireland","phone":"6086347426"},
{"id":111,"first_name":"Rachael","last_name":"Rainbow","email":"rrainbow32@globo.com","date_of_birth":"11/23/2017","age":53,"country":"Ukraine","phone":"6172617054"},
{"id":112,"first_name":"Jessey","last_name":"Spilsburie","email":"jspilsburie33@wufoo.com","date_of_birth":"10/18/1970","age":58,"country":"Brazil","phone":"5965174372"},
{"id":113,"first_name":"Benetta","last_name":"Van Dalen","email":"bvandalen34@bing.com","date_of_birth":"12/15/2006","age":23,"country":"Poland","phone":"1166747471"},
{"id":114,"first_name":"Morganne","last_name":"Sangwin","email":"msangwin35@google.nl","date_of_birth":"3/30/1975","age":57,"country":"Estonia","phone":"7371382480"},
{"id":115,"first_name":"Rozele","last_name":"Aleksic","email":"raleksic36@nih.gov","date_of_birth":"5/25/1995","age":57,"country":"Japan","phone":"2584634741"},
{"id":116,"first_name":"Dell","last_name":"Gery","email":"dgery37@jiathis.com","date_of_birth":"5/11/1987","age":47,"country":"Honduras","phone":"6832094097"},
{"id":117,"first_name":"Neala","last_name":"Vanner","email":"nvanner38@bing.com","date_of_birth":"10/7/1986","age":48,"country":"Russia","phone":"1393645240"},
{"id":118,"first_name":"Jerald","last_name":"Jee","email":"jjee39@princeton.edu","date_of_birth":"11/23/2005","age":40,"country":"Indonesia","phone":"2895560882"},
{"id":119,"first_name":"Pail","last_name":"Benasik","email":"pbenasik3a@google.com.au","date_of_birth":"3/29/1972","age":23,"country":"Peru","phone":"5332552446"},
{"id":120,"first_name":"Catherine","last_name":"Ludwikiewicz","email":"cludwikiewicz3b@nyu.edu","date_of_birth":"2/14/2009","age":33,"country":"Philippines","phone":"4122902765"},
{"id":121,"first_name":"Cull","last_name":"Dallewater","email":"cdallewater3c@51.la","date_of_birth":"7/17/1974","age":37,"country":"Kazakhstan","phone":"6916302994"},
{"id":122,"first_name":"Yankee","last_name":"Blunderfield","email":"yblunderfield3d@blog.com","date_of_birth":"12/4/2009","age":29,"country":"Indonesia","phone":"8327303228"},
{"id":123,"first_name":"Ashlin","last_name":"Bonevant","email":"abonevant3e@oakley.com","date_of_birth":"6/11/1982","age":42,"country":"Philippines","phone":"4792672585"},
{"id":124,"first_name":"Honoria","last_name":"Pringuer","email":"hpringuer3f@google.pl","date_of_birth":"9/28/2009","age":45,"country":"Guyana","phone":"4929764720"},
{"id":125,"first_name":"Aldin","last_name":"Forber","email":"aforber3g@cnet.com","date_of_birth":"9/27/1996","age":54,"country":"Russia","phone":"6972614426"},
{"id":126,"first_name":"Tally","last_name":"Romushkin","email":"tromushkin3h@usa.gov","date_of_birth":"7/16/1972","age":37,"country":"Nigeria","phone":"9637338982"},
{"id":127,"first_name":"Eryn","last_name":"Kerford","email":"ekerford3i@state.tx.us","date_of_birth":"3/16/1972","age":38,"country":"France","phone":"1986279814"},
{"id":128,"first_name":"Andriette","last_name":"Bortolomei","email":"abortolomei3j@narod.ru","date_of_birth":"11/8/1986","age":45,"country":"Ukraine","phone":"4019917270"},
{"id":129,"first_name":"Maury","last_name":"Done","email":"mdone3k@washingtonpost.com","date_of_birth":"9/15/2019","age":47,"country":"China","phone":"5344970190"},
{"id":130,"first_name":"Daryle","last_name":"Kelle","email":"dkelle3l@stumbleupon.com","date_of_birth":"8/7/2013","age":47,"country":"Indonesia","phone":"5006911392"},
{"id":131,"first_name":"Tybalt","last_name":"O'Shirine","email":"toshirine3m@yellowbook.com","date_of_birth":"9/18/2012","age":29,"country":"China","phone":"8693730323"},
{"id":132,"first_name":"Karilynn","last_name":"Stoffersen","email":"kstoffersen3n@springer.com","date_of_birth":"5/18/2004","age":37,"country":"Philippines","phone":"7668699360"},
{"id":133,"first_name":"Reeva","last_name":"Faulconer","email":"rfaulconer3o@odnoklassniki.ru","date_of_birth":"4/28/1973","age":49,"country":"Ukraine","phone":"3985523896"},
{"id":134,"first_name":"Latia","last_name":"Beekman","email":"lbeekman3p@ow.ly","date_of_birth":"4/7/1975","age":21,"country":"Portugal","phone":"2918451322"},
{"id":135,"first_name":"Melvyn","last_name":"Haslock","email":"mhaslock3q@storify.com","date_of_birth":"3/5/1971","age":34,"country":"Vietnam","phone":"2864016879"},
{"id":136,"first_name":"Wayland","last_name":"Fevers","email":"wfevers3r@timesonline.co.uk","date_of_birth":"5/4/2003","age":39,"country":"Botswana","phone":"9679851169"},
{"id":137,"first_name":"Dalt","last_name":"Ibell","email":"dibell3s@typepad.com","date_of_birth":"9/5/1986","age":45,"country":"Japan","phone":"7677507292"},
{"id":138,"first_name":"Tawnya","last_name":"Bavidge","email":"tbavidge3t@howstuffworks.com","date_of_birth":"5/5/2011","age":26,"country":"Peru","phone":"9044901938"},
{"id":139,"first_name":"Reider","last_name":"Guidi","email":"rguidi3u@youku.com","date_of_birth":"4/14/2013","age":21,"country":"Canada","phone":"7995400495"},
{"id":140,"first_name":"Daune","last_name":"Double","email":"ddouble3v@posterous.com","date_of_birth":"2/16/1988","age":28,"country":"Philippines","phone":"5652930844"},
{"id":141,"first_name":"Holden","last_name":"Saunders","email":"hsaunders3w@whitehouse.gov","date_of_birth":"7/1/1991","age":34,"country":"Poland","phone":"4439290085"},
{"id":142,"first_name":"Shalna","last_name":"Sircombe","email":"ssircombe3x@gmpg.org","date_of_birth":"9/11/1992","age":26,"country":"Honduras","phone":"2203659855"},
{"id":143,"first_name":"Angelia","last_name":"Carah","email":"acarah3y@ftc.gov","date_of_birth":"9/2/1986","age":28,"country":"Poland","phone":"3364876257"},
{"id":144,"first_name":"Jody","last_name":"Benedicte","email":"jbenedicte3z@independent.co.uk","date_of_birth":"5/21/1987","age":22,"country":"Netherlands","phone":"9294812092"},
{"id":145,"first_name":"Lukas","last_name":"McMillian","email":"lmcmillian40@eventbrite.com","date_of_birth":"6/1/1972","age":42,"country":"China","phone":"8063574110"},
{"id":146,"first_name":"Lisabeth","last_name":"Capel","email":"lcapel41@house.gov","date_of_birth":"5/31/2018","age":44,"country":"China","phone":"1229763386"},
{"id":147,"first_name":"Cati","last_name":"Dumbelton","email":"cdumbelton42@fastcompany.com","date_of_birth":"6/20/2019","age":23,"country":"France","phone":"5055711281"},
{"id":148,"first_name":"Martita","last_name":"Kalderon","email":"mkalderon43@newsvine.com","date_of_birth":"8/20/1992","age":41,"country":"China","phone":"6807354413"},
{"id":149,"first_name":"Cammie","last_name":"Leppington","email":"cleppington44@twitpic.com","date_of_birth":"4/21/1986","age":32,"country":"Spain","phone":"8456761765"},
{"id":150,"first_name":"Brose","last_name":"Flemming","email":"bflemming45@odnoklassniki.ru","date_of_birth":"11/7/1989","age":29,"country":"South Africa","phone":"4499672569"},
{"id":151,"first_name":"Erin","last_name":"Assante","email":"eassante46@wordpress.org","date_of_birth":"3/9/2013","age":18,"country":"China","phone":"4695452929"},
{"id":152,"first_name":"Zandra","last_name":"Simnell","email":"zsimnell47@histats.com","date_of_birth":"3/9/1975","age":28,"country":"China","phone":"9362926592"},
{"id":153,"first_name":"Fionnula","last_name":"Deniskevich","email":"fdeniskevich48@google.co.jp","date_of_birth":"11/19/1990","age":54,"country":"Ukraine","phone":"7073551119"},
{"id":154,"first_name":"Pearle","last_name":"Norrey","email":"pnorrey49@stanford.edu","date_of_birth":"8/20/2004","age":29,"country":"Greece","phone":"4913849911"},
{"id":155,"first_name":"Hi","last_name":"Itzchaki","email":"hitzchaki4a@harvard.edu","date_of_birth":"10/7/1994","age":30,"country":"Czech Republic","phone":"1142489276"},
{"id":156,"first_name":"Cindelyn","last_name":"Riley","email":"criley4b@vimeo.com","date_of_birth":"10/1/1987","age":40,"country":"Brazil","phone":"9891305697"},
{"id":157,"first_name":"Aluino","last_name":"Gasticke","email":"agasticke4c@mashable.com","date_of_birth":"1/12/1972","age":51,"country":"Serbia","phone":"9824328859"},
{"id":158,"first_name":"Marc","last_name":"Chopin","email":"mchopin4d@tamu.edu","date_of_birth":"10/26/1979","age":48,"country":"Poland","phone":"8235016790"},
{"id":159,"first_name":"Wandie","last_name":"Kempster","email":"wkempster4e@accuweather.com","date_of_birth":"4/5/1999","age":22,"country":"Venezuela","phone":"4088365879"},
{"id":160,"first_name":"Abby","last_name":"McIlherran","email":"amcilherran4f@tuttocitta.it","date_of_birth":"1/1/1975","age":26,"country":"China","phone":"9899389992"},
{"id":161,"first_name":"Justus","last_name":"Capstake","email":"jcapstake4g@apple.com","date_of_birth":"2/25/1981","age":35,"country":"Philippines","phone":"1184736170"},
{"id":162,"first_name":"Drake","last_name":"Simeons","email":"dsimeons4h@theguardian.com","date_of_birth":"11/19/2004","age":43,"country":"Philippines","phone":"6134452800"},
{"id":163,"first_name":"Gusta","last_name":"Sleath","email":"gsleath4i@senate.gov","date_of_birth":"5/9/2019","age":19,"country":"Philippines","phone":"1846431210"},
{"id":164,"first_name":"Ferne","last_name":"Cardo","email":"fcardo4j@china.com.cn","date_of_birth":"4/23/2015","age":49,"country":"Thailand","phone":"1154040127"},
{"id":165,"first_name":"Amery","last_name":"Creelman","email":"acreelman4k@chronoengine.com","date_of_birth":"10/16/1986","age":28,"country":"China","phone":"4377261303"},
{"id":166,"first_name":"Rockey","last_name":"Tunstall","email":"rtunstall4l@altervista.org","date_of_birth":"8/2/2004","age":20,"country":"Denmark","phone":"2625474272"},
{"id":167,"first_name":"Stefano","last_name":"Houlworth","email":"shoulworth4m@washingtonpost.com","date_of_birth":"3/3/1978","age":34,"country":"Indonesia","phone":"5228586530"},
{"id":168,"first_name":"Jeana","last_name":"Gumley","email":"jgumley4n@bigcartel.com","date_of_birth":"2/27/1985","age":42,"country":"Philippines","phone":"3409457123"},
{"id":169,"first_name":"Baily","last_name":"Carles","email":"bcarles4o@army.mil","date_of_birth":"11/13/1978","age":49,"country":"Croatia","phone":"7342888904"},
{"id":170,"first_name":"Neddy","last_name":"McDell","email":"nmcdell4p@squarespace.com","date_of_birth":"9/14/2015","age":23,"country":"Hungary","phone":"3452225973"},
{"id":171,"first_name":"Andrei","last_name":"Mawford","email":"amawford4q@alibaba.com","date_of_birth":"8/10/1980","age":23,"country":"Portugal","phone":"5179224531"},
{"id":172,"first_name":"Lona","last_name":"Bellon","email":"lbellon4r@ucla.edu","date_of_birth":"11/22/2011","age":31,"country":"China","phone":"9539396330"},
{"id":173,"first_name":"Coretta","last_name":"Dello","email":"cdello4s@tmall.com","date_of_birth":"9/26/1980","age":54,"country":"Bosnia and Herzegovina","phone":"1164234266"},
{"id":174,"first_name":"Niles","last_name":"Minico","email":"nminico4t@sakura.ne.jp","date_of_birth":"5/10/1975","age":47,"country":"Japan","phone":"9782706430"},
{"id":175,"first_name":"Ashien","last_name":"Stopforth","email":"astopforth4u@mysql.com","date_of_birth":"1/4/1996","age":32,"country":"Czech Republic","phone":"3464240659"},
{"id":176,"first_name":"Garv","last_name":"Samms","email":"gsamms4v@alibaba.com","date_of_birth":"10/24/1971","age":47,"country":"Thailand","phone":"7681668541"},
{"id":177,"first_name":"Elizabeth","last_name":"Fero","email":"efero4w@vistaprint.com","date_of_birth":"9/14/2020","age":28,"country":"Portugal","phone":"9508155739"},
{"id":178,"first_name":"George","last_name":"Readitt","email":"greaditt4x@upenn.edu","date_of_birth":"12/15/1992","age":56,"country":"China","phone":"1198517540"},
{"id":179,"first_name":"Kanya","last_name":"Broadberry","email":"kbroadberry4y@apple.com","date_of_birth":"11/13/1991","age":57,"country":"Thailand","phone":"5305140624"},
{"id":180,"first_name":"Imogene","last_name":"Robatham","email":"irobatham4z@fc2.com","date_of_birth":"1/15/1975","age":25,"country":"Sweden","phone":"1219118294"},
{"id":181,"first_name":"Pavla","last_name":"Wadge","email":"pwadge50@geocities.com","date_of_birth":"6/23/2011","age":53,"country":"Brazil","phone":"8723646372"},
{"id":182,"first_name":"Donnie","last_name":"Melmoth","email":"dmelmoth51@fema.gov","date_of_birth":"3/16/1981","age":28,"country":"Pakistan","phone":"4062040626"},
{"id":183,"first_name":"Doralia","last_name":"Tortis","email":"dtortis52@google.es","date_of_birth":"2/2/2016","age":58,"country":"China","phone":"1078300531"},
{"id":184,"first_name":"Eve","last_name":"Meiklam","email":"emeiklam53@arizona.edu","date_of_birth":"4/20/1989","age":51,"country":"China","phone":"1608170123"},
{"id":185,"first_name":"Maryrose","last_name":"Avramovich","email":"mavramovich54@columbia.edu","date_of_birth":"5/8/1993","age":37,"country":"China","phone":"9688952981"},
{"id":186,"first_name":"Quinn","last_name":"Grimble","email":"qgrimble55@godaddy.com","date_of_birth":"9/5/1971","age":57,"country":"Ukraine","phone":"6906412527"},
{"id":187,"first_name":"Sheridan","last_name":"Joynt","email":"sjoynt56@cornell.edu","date_of_birth":"3/9/1989","age":54,"country":"Iran","phone":"3885699876"},
{"id":188,"first_name":"Brewer","last_name":"Rochewell","email":"brochewell57@apache.org","date_of_birth":"3/23/1976","age":31,"country":"Indonesia","phone":"1963581883"},
{"id":189,"first_name":"Karoly","last_name":"Yanshonok","email":"kyanshonok58@cbsnews.com","date_of_birth":"11/29/1993","age":37,"country":"China","phone":"2966151140"},
{"id":190,"first_name":"Jim","last_name":"Schafer","email":"jschafer59@mozilla.com","date_of_birth":"12/7/2004","age":35,"country":"Brazil","phone":"2127541269"},
{"id":191,"first_name":"Thatcher","last_name":"Earingey","email":"tearingey5a@state.tx.us","date_of_birth":"7/22/2019","age":46,"country":"Philippines","phone":"4672497170"},
{"id":192,"first_name":"Clerc","last_name":"Bamborough","email":"cbamborough5b@storify.com","date_of_birth":"11/6/1985","age":58,"country":"Colombia","phone":"7982274604"},
{"id":193,"first_name":"Purcell","last_name":"Voller","email":"pvoller5c@dailymail.co.uk","date_of_birth":"5/13/1975","age":27,"country":"Spain","phone":"4263915372"},
{"id":194,"first_name":"Guthrey","last_name":"Skaife","email":"gskaife5d@g.co","date_of_birth":"5/24/1984","age":51,"country":"South Africa","phone":"9422332965"},
{"id":195,"first_name":"Travis","last_name":"Bernardeschi","email":"tbernardeschi5e@reverbnation.com","date_of_birth":"8/11/1983","age":36,"country":"Brazil","phone":"3467301485"},
{"id":196,"first_name":"Ingar","last_name":"Guinan","email":"iguinan5f@ucoz.ru","date_of_birth":"1/8/2016","age":45,"country":"China","phone":"7519862036"},
{"id":197,"first_name":"Hastings","last_name":"Edeler","email":"hedeler5g@nhs.uk","date_of_birth":"11/20/2016","age":28,"country":"China","phone":"5796746445"},
{"id":198,"first_name":"Hedwiga","last_name":"Gniewosz","email":"hgniewosz5h@istockphoto.com","date_of_birth":"10/16/2018","age":35,"country":"Portugal","phone":"2785442427"},
{"id":199,"first_name":"Thorny","last_name":"Tarquini","email":"ttarquini5i@salon.com","date_of_birth":"6/22/2006","age":46,"country":"Iran","phone":"6084099933"},
{"id":200,"first_name":"Tommy","last_name":"Handyside","email":"thandyside5j@stumbleupon.com","date_of_birth":"8/1/1977","age":23,"country":"Armenia","phone":"1013920944"}]